spotils/__init__.py
spotils/__main__.py
spotils/cli.py
spotils/client.py
spotils/config.py
spotils/dev/__init__.py
spotils/dev/inspect_response.py
spotils/dev/verbose_liked_songs_playlist.py
spotils/helpers/__init__.py
spotils/helpers/fetch_tracks.py
spotils/helpers/logging.py
spotils/helpers/scheduler.py
spotils/helpers/time.py
spotils/helpers/tracks_cache.py
spotils/models.py
spotils/utils/__init__.py
spotils/utils/liked_songs_sync.py
spotils/utils/recently_played.py
spotils/utils/skip_liked.py
spotils-0.1.0.dist-info/entry_points.txt
spotils-0.1.0.dist-info/LICENSE
spotils-0.1.0.dist-info/WHEEL
spotils-0.1.0.dist-info/METADATA
spotils-0.1.0.dist-info/RECORD
