Metadata-Version: 2.1
Name: spotils
Version: 0.1.0
Summary: A few utilities for providing a smoother Spotify experience.
Home-page: https://github.com/Qwerty-133/spotils
License: MIT
Author: Qwerty-133
Author-email: 74311372+Qwerty-133@users.noreply.github.com
Requires-Python: >=3.10,<4.0
Classifier: Development Status :: 2 - Pre-Alpha
Classifier: Environment :: Console
Classifier: Framework :: Flake8
Classifier: License :: OSI Approved :: MIT License
Classifier: Natural Language :: English
Classifier: Operating System :: MacOS
Classifier: Operating System :: Microsoft :: Windows
Classifier: Operating System :: POSIX :: Linux
Classifier: Programming Language :: Python :: 3
Classifier: Programming Language :: Python :: 3.10
Classifier: Programming Language :: Python :: 3.11
Classifier: Programming Language :: Python :: 3.10
Classifier: Programming Language :: Python :: 3.11
Classifier: Topic :: Internet
Classifier: Topic :: Utilities
Classifier: Typing :: Typed
Requires-Dist: arrow (>=1.2.3,<2.0.0)
Requires-Dist: loguru (>=0.6.0,<0.7.0)
Requires-Dist: mergedeep (>=1.3.4,<2.0.0)
Requires-Dist: python-dateutil (>=2.8.2,<3.0.0)
Requires-Dist: python-dotenv (>=0.21.0,<0.22.0)
Requires-Dist: rich (>=12.6.0,<13.0.0)
Requires-Dist: schedule (>=1.1.0,<2.0.0)
Requires-Dist: spotipy (>=2.21.0,<3.0.0)
Requires-Dist: typer (>=0.7.0,<0.8.0)
Project-URL: Repository, https://github.com/Qwerty-133/spotils
